oexp/__init__.py
oexp/access.py
oexp/gen.py
oexp/jbridge.py
oexp/util/__init__.py
oexp/util/ops.py
oexp/util/vals.py
oexp-0.15.0.dist-info/METADATA
oexp-0.15.0.dist-info/WHEEL
oexp-0.15.0.dist-info/top_level.txt
oexp-0.15.0.dist-info/RECORD
