Metadata-Version: 2.1
Name: oexp
Version: 0.15.0
Summary: Online Experiments
Author-email: Matt Groth <mjgroth@mit.edu>
Requires-Dist: requests
Requires-Dist: aiohttp
Requires-Dist: tqdm
Requires-Dist: mstuff ==0.7.12
